PKG-INFO
README
setup.cfg
setup.py
speedyxml.egg-info/PKG-INFO
speedyxml.egg-info/SOURCES.txt
speedyxml.egg-info/dependency_links.txt
speedyxml.egg-info/top_level.txt
src/speedyxml.c
src/speedyxml.pyi
src/speedyxml.egg-info/PKG-INFO
src/speedyxml.egg-info/SOURCES.txt
src/speedyxml.egg-info/dependency_links.txt
src/speedyxml.egg-info/top_level.txt
test/1.result
test/1.test
test/10.result
test/10.test
test/11.result
test/11.test
test/12.result
test/12.test
test/13.result
test/13.test
test/14.result
test/14.test
test/15.result
test/15.test
test/16.result
test/16.test
test/17.result
test/17.test
test/18.result
test/18.test
test/19.result
test/19.test
test/2.result
test/2.test
test/20.result
test/20.test
test/21.result
test/21.test
test/22.result
test/22.test
test/23.result
test/23.test
test/24.result
test/24.test
test/25.result
test/25.test
test/26.result
test/26.test
test/27.result
test/27.test
test/28.result
test/28.test
test/29.result
test/29.test
test/3.result
test/3.test
test/30.result
test/30.test
test/31.result
test/31.test
test/32.result
test/32.test
test/33.result
test/33.test
test/34.result
test/34.test
test/35.result
test/35.test
test/4.result
test/4.test
test/5.result
test/5.test
test/6.result
test/6.test
test/7.result
test/7.test
test/8.result
test/8.test
test/9.result
test/9.test
test/__init__.py
test/test.py