Metadata-Version: 2.4
Name: speedyxml
Version: 0.4.0.8
Summary: Speedy XML parser for Python
Author: kilroy
Author-email: kilroy@81818.de
License: LGPL
Classifier: Development Status :: 4 - Beta
Classifier: Intended Audience :: Developers
Classifier: Natural Language :: English
Classifier: Operating System :: POSIX
Classifier: Programming Language :: Python
Classifier: Programming Language :: Python :: 3
Classifier: Topic :: Software Development :: Libraries :: Python Modules
Classifier: Topic :: Text Processing :: Markup :: XML
Classifier: License :: OSI Approved :: GNU Library or Lesser General Public License (LGPL)
Dynamic: author
Dynamic: author-email
Dynamic: classifier
Dynamic: description
Dynamic: description-content-type
Dynamic: license
Dynamic: summary
